byte_triggers/__init__.py
byte_triggers/_base.py
byte_triggers/_version.py
byte_triggers/lsl.py
byte_triggers/mock.py
byte_triggers/parallel.py
byte_triggers/commands/__init__.py
byte_triggers/commands/sys_info.py
byte_triggers/io/__init__.py
byte_triggers/io/_dlportio.py
byte_triggers/io/_inpout.py
byte_triggers/io/_linux.py
byte_triggers/utils/__init__.py
byte_triggers/utils/_checks.py
byte_triggers/utils/_docs.py
byte_triggers/utils/_fixes.py
byte_triggers/utils/_imports.py
byte_triggers/utils/config.py
byte_triggers/utils/logs.py
byte_triggers-0.4.1.dist-info/LICENSE
byte_triggers-0.4.1.dist-info/METADATA
byte_triggers-0.4.1.dist-info/WHEEL
byte_triggers-0.4.1.dist-info/entry_points.txt
byte_triggers-0.4.1.dist-info/top_level.txt
byte_triggers-0.4.1.dist-info/RECORD
