Metadata-Version: 2.1
Name: byte_triggers
Version: 0.4.1
Summary: Provides byte (0 to 255) triggers on serial/parallel ports and on LSL streams.
Author-email: Mathieu Scheltienne <mathieu.scheltienne@fcbg.ch>
Maintainer-email: Mathieu Scheltienne <mathieu.scheltienne@fcbg.ch>
License: MIT License
Project-URL: documentation, https://fcbg-platforms.github.io/byte-triggers
Project-URL: source, https://github.com/fcbg-platforms/byte-triggers
Project-URL: tracker, https://github.com/fcbg-platforms/byte-triggers/issues
Keywords: events,lsl,parallel,python,serial,triggers
Classifier: License :: OSI Approved :: MIT License
Classifier: Natural Language :: English
Classifier: Operating System :: MacOS
Classifier: Operating System :: Microsoft :: Windows
Classifier: Operating System :: Unix
Classifier: Programming Language :: Python :: 3 :: Only
Classifier: Programming Language :: Python :: 3.10
Classifier: Programming Language :: Python :: 3.11
Classifier: Programming Language :: Python :: 3.12
Classifier: Programming Language :: Python :: 3.9
Requires-Python: >=3.9
License-File: LICENSE
Requires-Dist: mne-lsl >=1.3.1
Requires-Dist: numpy >=1.26.4
Requires-Dist: packaging
Requires-Dist: psutil
Requires-Dist: pyserial
Requires-Dist: pyparallel ; sys_platform == "linux"
Provides-Extra: all
Requires-Dist: byte-triggers[build] ; extra == 'all'
Requires-Dist: byte-triggers[doc] ; extra == 'all'
Requires-Dist: byte-triggers[style] ; extra == 'all'
Requires-Dist: byte-triggers[test] ; extra == 'all'
Provides-Extra: build
Requires-Dist: build ; extra == 'build'
Requires-Dist: twine ; extra == 'build'
Provides-Extra: doc
Requires-Dist: furo ; extra == 'doc'
Requires-Dist: intersphinx-registry ; extra == 'doc'
Requires-Dist: matplotlib ; extra == 'doc'
Requires-Dist: memory-profiler ; extra == 'doc'
Requires-Dist: numpydoc ; extra == 'doc'
Requires-Dist: sphinx ; extra == 'doc'
Requires-Dist: sphinx-copybutton ; extra == 'doc'
Requires-Dist: sphinx-design ; extra == 'doc'
Requires-Dist: sphinx-issues ; extra == 'doc'
Requires-Dist: sphinx-remove-toctrees ; extra == 'doc'
Requires-Dist: sphinxcontrib-bibtex ; extra == 'doc'
Provides-Extra: full
Requires-Dist: byte-triggers[all] ; extra == 'full'
Provides-Extra: style
Requires-Dist: bibclean ; extra == 'style'
Requires-Dist: codespell[toml] >=2.2.4 ; extra == 'style'
Requires-Dist: isort ; extra == 'style'
Requires-Dist: pydocstyle[toml] ; extra == 'style'
Requires-Dist: ruff >=0.1.8 ; extra == 'style'
Requires-Dist: toml-sort ; extra == 'style'
Requires-Dist: yamllint ; extra == 'style'
Provides-Extra: test
Requires-Dist: pytest-cov ; extra == 'test'
Requires-Dist: pytest-timeout ; extra == 'test'
Requires-Dist: pytest >=8.0 ; extra == 'test'
